autoscaler_service/__init__.py
autoscaler_service/version.py
autoscaler_service/commands/__init__.py
autoscaler_service/commands/main.py
autoscaler_service/requests/__init__.py
autoscaler_service/requests/requests.py
autoscaler_service/requests/results.py
autoscaler_service/server/__init__.py
autoscaler_service/server/apply_decorators.py
autoscaler_service/server/handler.py
autoscaler_service/server/server.py
autoscaler_service/server/update_builtin.py
everai_builtin_autoscaler_service-0.0.6.dist-info/METADATA
everai_builtin_autoscaler_service-0.0.6.dist-info/WHEEL
everai_builtin_autoscaler_service-0.0.6.dist-info/entry_points.txt
everai_builtin_autoscaler_service-0.0.6.dist-info/top_level.txt
everai_builtin_autoscaler_service-0.0.6.dist-info/RECORD
